google/cloud/modelarmor/__init__.py
google/cloud/modelarmor/gapic_version.py
google/cloud/modelarmor/py.typed
google/cloud/modelarmor_v1/__init__.py
google/cloud/modelarmor_v1/gapic_metadata.json
google/cloud/modelarmor_v1/gapic_version.py
google/cloud/modelarmor_v1/py.typed
google/cloud/modelarmor_v1/services/__init__.py
google/cloud/modelarmor_v1/services/model_armor/__init__.py
google/cloud/modelarmor_v1/services/model_armor/async_client.py
google/cloud/modelarmor_v1/services/model_armor/client.py
google/cloud/modelarmor_v1/services/model_armor/pagers.py
google/cloud/modelarmor_v1/services/model_armor/transports/__init__.py
google/cloud/modelarmor_v1/services/model_armor/transports/base.py
google/cloud/modelarmor_v1/services/model_armor/transports/grpc.py
google/cloud/modelarmor_v1/services/model_armor/transports/grpc_asyncio.py
google/cloud/modelarmor_v1/services/model_armor/transports/rest.py
google/cloud/modelarmor_v1/services/model_armor/transports/rest_base.py
google/cloud/modelarmor_v1/types/__init__.py
google/cloud/modelarmor_v1/types/service.py
google/cloud/modelarmor_v1beta/__init__.py
google/cloud/modelarmor_v1beta/gapic_metadata.json
google/cloud/modelarmor_v1beta/gapic_version.py
google/cloud/modelarmor_v1beta/py.typed
google/cloud/modelarmor_v1beta/services/__init__.py
google/cloud/modelarmor_v1beta/services/model_armor/__init__.py
google/cloud/modelarmor_v1beta/services/model_armor/async_client.py
google/cloud/modelarmor_v1beta/services/model_armor/client.py
google/cloud/modelarmor_v1beta/services/model_armor/pagers.py
google/cloud/modelarmor_v1beta/services/model_armor/transports/__init__.py
google/cloud/modelarmor_v1beta/services/model_armor/transports/base.py
google/cloud/modelarmor_v1beta/services/model_armor/transports/grpc.py
google/cloud/modelarmor_v1beta/services/model_armor/transports/grpc_asyncio.py
google/cloud/modelarmor_v1beta/services/model_armor/transports/rest.py
google_cloud_modelarmor-0.3.0.dist-info/licenses/LICENSE
google_cloud_modelarmor-0.3.0.dist-info/METADATA
google_cloud_modelarmor-0.3.0.dist-info/WHEEL
google_cloud_modelarmor-0.3.0.dist-info/top_level.txt
google_cloud_modelarmor-0.3.0.dist-info/RECORD
